adsg_core/__init__.py
adsg_core/func_cache.py
adsg_core/render.py
adsg_core/examples/__init__.py
adsg_core/examples/apollo.py
adsg_core/examples/gnc.py
adsg_core/graph/__init__.py
adsg_core/graph/adsg.py
adsg_core/graph/adsg_basic.py
adsg_core/graph/adsg_nodes.py
adsg_core/graph/choice_constraints.py
adsg_core/graph/choices.py
adsg_core/graph/export.py
adsg_core/graph/graph_edges.py
adsg_core/graph/incompatibility.py
adsg_core/graph/influence_matrix.py
adsg_core/graph/traversal.py
adsg_core/graph/sup/__init__.py
adsg_core/graph/sup/dsg.py
adsg_core/graph/sup/nodes.py
adsg_core/optimization/__init__.py
adsg_core/optimization/dv_output_defs.py
adsg_core/optimization/evaluator.py
adsg_core/optimization/graph_processor.py
adsg_core/optimization/problem.py
adsg_core/optimization/assign_enc/__init__.py
adsg_core/optimization/assign_enc/assignment_manager.py
adsg_core/optimization/assign_enc/cache.py
adsg_core/optimization/assign_enc/encoder_registry.py
adsg_core/optimization/assign_enc/encoding.py
adsg_core/optimization/assign_enc/lazy_encoding.py
adsg_core/optimization/assign_enc/matrix.py
adsg_core/optimization/assign_enc/selector.py
adsg_core/optimization/assign_enc/time_limiter.py
adsg_core/optimization/assign_enc/eager/__init__.py
adsg_core/optimization/assign_enc/eager/encodings/__init__.py
adsg_core/optimization/assign_enc/eager/encodings/direct_matrix.py
adsg_core/optimization/assign_enc/eager/encodings/group_amount.py
adsg_core/optimization/assign_enc/eager/encodings/group_element.py
adsg_core/optimization/assign_enc/eager/encodings/grouped_base.py
adsg_core/optimization/assign_enc/eager/imputation/__init__.py
adsg_core/optimization/assign_enc/eager/imputation/auto_mod.py
adsg_core/optimization/assign_enc/eager/imputation/closest.py
adsg_core/optimization/assign_enc/eager/imputation/constraint_violation.py
adsg_core/optimization/assign_enc/eager/imputation/delta.py
adsg_core/optimization/assign_enc/eager/imputation/first.py
adsg_core-1.3.1.dist-info/licenses/LICENSE
adsg_core-1.3.1.dist-info/METADATA
adsg_core-1.3.1.dist-info/WHEEL
adsg_core-1.3.1.dist-info/top_level.txt
adsg_core-1.3.1.dist-info/RECORD
