Metadata-Version: 2.4
Name: adsg-core
Version: 1.3.1
Summary: Design Space Graph (ADSG Core)
Author: Jasper Bussemaker
Author-email: jasper.bussemaker@dlr.de
License: MIT
Classifier: Intended Audience :: Science/Research
Classifier: Topic :: Scientific/Engineering
Classifier: Programming Language :: Python :: 3
Classifier: License :: OSI Approved :: MIT License
Requires-Python: >=3.7
License-File: LICENSE
Requires-Dist: networkx~=2.6
Requires-Dist: lxml
Requires-Dist: pydot
Requires-Dist: cached-property>=1.5
Requires-Dist: appdirs
Requires-Dist: numpy<2.0
Requires-Dist: scipy~=1.9
Requires-Dist: pandas
Requires-Dist: numba~=0.56
Requires-Dist: natsort
Provides-Extra: opt
Requires-Dist: sb-arch-opt~=1.5; extra == "opt"
Provides-Extra: nb
Requires-Dist: jupyter; extra == "nb"
Requires-Dist: ipython; extra == "nb"
Requires-Dist: ipykernel; extra == "nb"
Requires-Dist: matplotlib; extra == "nb"
Dynamic: license-file
